jaxkern/__init__.py
jaxkern/_version.py
jaxkern/base.py
jaxkern/computations/__init__.py
jaxkern/computations/base.py
jaxkern/computations/constant_diagonal.py
jaxkern/computations/dense.py
jaxkern/computations/diagonal.py
jaxkern/computations/eigen.py
jaxkern/non_euclidean/__init__.py
jaxkern/non_euclidean/graph.py
jaxkern/non_euclidean/utils.py
jaxkern/nonstationary/__init__.py
jaxkern/nonstationary/linear.py
jaxkern/nonstationary/polynomial.py
jaxkern/stationary/__init__.py
jaxkern/stationary/matern12.py
jaxkern/stationary/matern32.py
jaxkern/stationary/matern52.py
jaxkern/stationary/periodic.py
jaxkern/stationary/powered_exponential.py
jaxkern/stationary/rational_quadratic.py
jaxkern/stationary/rbf.py
jaxkern/stationary/utils.py
jaxkern/stationary/white.py
jaxkern-0.0.5.dist-info/LICENSE
jaxkern-0.0.5.dist-info/METADATA
jaxkern-0.0.5.dist-info/WHEEL
jaxkern-0.0.5.dist-info/top_level.txt
jaxkern-0.0.5.dist-info/RECORD
