Metadata-Version: 2.1
Name: jaxkern
Version: 0.0.5
Summary: Kernels in Jax.
Home-page: UNKNOWN
Author: Daniel Dodd and Thomas Pinder
Author-email: tompinder@live.co.uk
License: LICENSE
Project-URL: Documentation, https://JaxKern.readthedocs.io/en/latest/
Project-URL: Source, https://github.com/JaxGaussianProcesses/JaxKern
Keywords: gaussian-processes jax machine-learning bayesian
Platform: UNKNOWN
Requires-Dist: jax (>=0.4.1)
Requires-Dist: jaxlib (>=0.4.1)
Requires-Dist: jaxutils (>=0.0.8)
Requires-Dist: jaxtyping (>=0.0.2)
Requires-Dist: jaxlinop (>=0.0.3)
Requires-Dist: deprecation
Provides-Extra: cuda
Requires-Dist: jax[cuda] ; extra == 'cuda'
Provides-Extra: dev
Requires-Dist: black ; extra == 'dev'
Requires-Dist: isort ; extra == 'dev'
Requires-Dist: pylint ; extra == 'dev'
Requires-Dist: flake8 ; extra == 'dev'
Requires-Dist: pytest ; extra == 'dev'
Requires-Dist: networkx ; extra == 'dev'
Requires-Dist: pytest-cov ; extra == 'dev'
Requires-Dist: pytest-xdist ; extra == 'dev'
